Metadata-Version: 2.1
Name: swagger2json
Version: 0.1.1
Summary: Generate request parameters from the Swagger json
Home-page: http://github.com/hhyo/swagger2json
Author: yuyu1987、hhyo
Author-email: rtttte@qq.com
License: Apache 2.0
Keywords: swagger swagger2json
Platform: UNKNOWN
Classifier: Development Status :: 3 - Alpha
Classifier: Intended Audience :: Developers
Classifier: License :: OSI Approved :: Apache Software License
Classifier: Operating System :: OS Independent
Classifier: Programming Language :: Python :: 2.7
Classifier: Programming Language :: Python :: 3
Classifier: Programming Language :: Python :: 3.4
Classifier: Programming Language :: Python :: 3.5
Classifier: Programming Language :: Python :: 3.6
Classifier: Programming Language :: Python :: 3.7
